unitmaster/__init__.py
unitmaster/cli.py
unitmaster/constants.py
unitmaster/converter.py
unitmaster/exceptions.py
unitmaster-0.1.0.dist-info/METADATA
unitmaster-0.1.0.dist-info/WHEEL
unitmaster-0.1.0.dist-info/entry_points.txt
unitmaster-0.1.0.dist-info/top_level.txt
unitmaster-0.1.0.dist-info/RECORD
